odoo/addons/sale_timesheet_rounded/README.rst
odoo/addons/sale_timesheet_rounded/__init__.py
odoo/addons/sale_timesheet_rounded/__manifest__.py
odoo/addons/sale_timesheet_rounded/hooks.py
odoo/addons/sale_timesheet_rounded/i18n/de.po
odoo/addons/sale_timesheet_rounded/i18n/es.po
odoo/addons/sale_timesheet_rounded/i18n/it.po
odoo/addons/sale_timesheet_rounded/i18n/nl.po
odoo/addons/sale_timesheet_rounded/i18n/sale_timesheet_rounded.pot
odoo/addons/sale_timesheet_rounded/models/__init__.py
odoo/addons/sale_timesheet_rounded/models/account_analytic_line.py
odoo/addons/sale_timesheet_rounded/models/project_project.py
odoo/addons/sale_timesheet_rounded/models/sale.py
odoo/addons/sale_timesheet_rounded/readme/CONFIGURE.rst
odoo/addons/sale_timesheet_rounded/readme/CONTRIBUTORS.rst
odoo/addons/sale_timesheet_rounded/readme/DESCRIPTION.rst
odoo/addons/sale_timesheet_rounded/readme/ROADMAP.rst
odoo/addons/sale_timesheet_rounded/static/description/icon.png
odoo/addons/sale_timesheet_rounded/static/description/index.html
odoo/addons/sale_timesheet_rounded/tests/__init__.py
odoo/addons/sale_timesheet_rounded/tests/test_rounded.py
odoo/addons/sale_timesheet_rounded/views/account_analytic_line.xml
odoo/addons/sale_timesheet_rounded/views/project_project.xml
odoo/addons/sale_timesheet_rounded/views/project_task.xml
odoo13_addon_sale_timesheet_rounded-13.0.1.0.1.dist-info/METADATA
odoo13_addon_sale_timesheet_rounded-13.0.1.0.1.dist-info/WHEEL
odoo13_addon_sale_timesheet_rounded-13.0.1.0.1.dist-info/top_level.txt
odoo13_addon_sale_timesheet_rounded-13.0.1.0.1.dist-info/RECORD
